landingai_ade/__init__.py
landingai_ade/_base_client.py
landingai_ade/_client.py
landingai_ade/_compat.py
landingai_ade/_constants.py
landingai_ade/_exceptions.py
landingai_ade/_files.py
landingai_ade/_models.py
landingai_ade/_qs.py
landingai_ade/_resource.py
landingai_ade/_response.py
landingai_ade/_streaming.py
landingai_ade/_types.py
landingai_ade/_version.py
landingai_ade/py.typed
landingai_ade/_utils/__init__.py
landingai_ade/_utils/_compat.py
landingai_ade/_utils/_datetime_parse.py
landingai_ade/_utils/_json.py
landingai_ade/_utils/_logs.py
landingai_ade/_utils/_proxy.py
landingai_ade/_utils/_reflection.py
landingai_ade/_utils/_resources_proxy.py
landingai_ade/_utils/_streams.py
landingai_ade/_utils/_sync.py
landingai_ade/_utils/_transform.py
landingai_ade/_utils/_typing.py
landingai_ade/_utils/_utils.py
landingai_ade/lib/.keep
landingai_ade/lib/__init__.py
landingai_ade/lib/schema_utils.py
landingai_ade/lib/url_utils.py
landingai_ade/resources/__init__.py
landingai_ade/resources/parse_jobs.py
landingai_ade/types/__init__.py
landingai_ade/types/client_extract_params.py
landingai_ade/types/client_parse_params.py
landingai_ade/types/client_split_params.py
landingai_ade/types/extract_response.py
landingai_ade/types/parse_job_create_params.py
landingai_ade/types/parse_job_create_response.py
landingai_ade/types/parse_job_get_response.py
landingai_ade/types/parse_job_list_params.py
landingai_ade/types/parse_job_list_response.py
landingai_ade/types/parse_response.py
landingai_ade/types/split_response.py
landingai_ade/types/shared/__init__.py
landingai_ade/types/shared/parse_grounding_box.py
landingai_ade/types/shared/parse_metadata.py
landingai_ade-1.5.0.dist-info/METADATA
landingai_ade-1.5.0.dist-info/WHEEL
landingai_ade-1.5.0.dist-info/licenses/LICENSE
landingai_ade-1.5.0.dist-info/RECORD
